coca.py
coca-1.0.1.dist-info/LICENSE.md
coca-1.0.1.dist-info/METADATA
coca-1.0.1.dist-info/WHEEL
coca-1.0.1.dist-info/top_level.txt
coca-1.0.1.dist-info/RECORD
